classy_sdk/__init__.py
classy_sdk/utils.py
classy_sdk/api/__init__.py
classy_sdk/api/api.py
classy_sdk/sdk/__init__.py
classy_sdk/sdk/sdk.py
searpent_classy_sdk-0.1.3.dist-info/LICENSE
searpent_classy_sdk-0.1.3.dist-info/METADATA
searpent_classy_sdk-0.1.3.dist-info/WHEEL
searpent_classy_sdk-0.1.3.dist-info/top_level.txt
searpent_classy_sdk-0.1.3.dist-info/RECORD
