Metadata-Version: 2.1
Name: searpent-classy-sdk
Version: 0.1.3
Summary: SDK for Searpent Classy API
Home-page: https://github.com/searpent/classy-sdk-python
Author: Searpent s.r.o.
Author-email: support@searpent.com
License: MIT License
Project-URL: API documentation, https://searpentclassy.docs.apiary.io
Classifier: Development Status :: 5 - Production/Stable
Classifier: License :: OSI Approved :: MIT License
Classifier: Programming Language :: Python :: 3
Classifier: Programming Language :: Python :: 3.6
Classifier: Programming Language :: Python :: 3.7
Classifier: Programming Language :: Python :: 3.8
Classifier: Programming Language :: Python :: 3.9
Classifier: Programming Language :: Python :: 3.10
Classifier: Operating System :: OS Independent
Requires-Python: >=3.6, <4
License-File: LICENSE
Requires-Dist: requests
